{
  "project_info": {
    "project_number": "519358432493",
    "firebase_url": "https://its-comunicacion-b06e8.firebaseio.com",
    "project_id": "its-comunicacion-b06e8",
    "storage_bucket": "its-comunicacion-b06e8.appspot.com"
  },
  "client": [
    {
      "client_info": {
        "mobilesdk_app_id": "1:519358432493:android:fa4b8be61c1012a0feb8e4",
        "android_client_info": {
          "package_name": "example.flutterapp.comunicacion"
        }
      },
      "oauth_client": [
        {
          "client_id": "519358432493-dadkdtnc8mg27mhcsovqc4gv44l22qk8.apps.googleusercontent.com",
          "client_type": 3
        }
      ],
      "api_key": [
        {
          "current_key": "AIzaSyC_oXgP7D4HW0ycnpmnwFPhOV4MS6qqONg"
        }
      ],
      "services": {
        "appinvite_service": {
          "other_platform_oauth_client": [
            {
              "client_id": "519358432493-dadkdtnc8mg27mhcsovqc4gv44l22qk8.apps.googleusercontent.com",
              "client_type": 3
            }
          ]
        }
      }
    }
  ],
  "configuration_version": "1"
}